pysof-0.1.30.dist-info/METADATA
pysof-0.1.30.dist-info/WHEEL
pysof/__init__.py
pysof/_pysof.cp312-win_amd64.pyd
pysof/_pysof.pyi
pysof/py.typed
pysof-0.1.30.dist-info/RECORD
