Metadata-Version: 2.4
Name: pysof
Version: 0.1.30
Classifier: Programming Language :: Python :: 3
Classifier: Programming Language :: Python :: 3.10
Classifier: Programming Language :: Python :: 3.11
Classifier: Programming Language :: Python :: 3.12
Classifier: Programming Language :: Python :: 3.13
Classifier: License :: OSI Approved :: MIT License
Classifier: Operating System :: OS Independent
Classifier: Development Status :: 4 - Beta
Classifier: Intended Audience :: Developers
Classifier: Intended Audience :: Healthcare Industry
Classifier: Topic :: Scientific/Engineering :: Medical Science Apps.
Classifier: Topic :: Software Development :: Libraries :: Python Modules
Summary: Python wrapper for the Helios Software SOF (SQL on FHIR) toolkit.
Keywords: SQL on FHIR,FHIR,healthcare,sof,Helios Software
Author-email: Helios Software <team@heliossoftware.com>
License: MIT
Requires-Python: >=3.10
Project-URL: Homepage, https://github.com/HeliosSoftware/hfs/tree/main/crates/pysof
Project-URL: Repository, https://github.com/HeliosSoftware/hfs
Project-URL: Documentation, https://github.com/HeliosSoftware/hfs/tree/main/crates/pysof
Project-URL: Bug Tracker, https://github.com/HeliosSoftware/hfs/issues
Project-URL: Source, https://github.com/HeliosSoftware/hfs/tree/main/crates/pysof
